graphit/__init__.py
graphit/graph.py
graphit/graph_exceptions.py
graphit/graph_helpers.py
graphit/graph_mixin.py
graphit/graph_networkx.py
graphit/graph_orm.py
graphit/graph_py2to3.py
graphit/graph_algorithms/__init__.py
graphit/graph_algorithms/centrality.py
graphit/graph_algorithms/connectivity.py
graphit/graph_algorithms/path_traversal.py
graphit/graph_algorithms/shortest_path.py
graphit/graph_axis/__init__.py
graphit/graph_axis/graph_axis_class.py
graphit/graph_axis/graph_axis_methods.py
graphit/graph_axis/graph_axis_mixin.py
graphit/graph_combinatorial/__init__.py
graphit/graph_combinatorial/graph_setlike_operations.py
graphit/graph_combinatorial/graph_split_join_operations.py
graphit/graph_combinatorial/graph_update_operations.py
graphit/graph_io/__init__.py
graphit/graph_io/io_cwl_format.py
graphit/graph_io/io_dot_format.py
graphit/graph_io/io_flattened_data_format.py
graphit/graph_io/io_helpers.py
graphit/graph_io/io_jgf_format.py
graphit/graph_io/io_json_format.py
graphit/graph_io/io_jsonschema_format.py
graphit/graph_io/io_jsonschema_format_drafts.py
graphit/graph_io/io_pgf_format.py
graphit/graph_io/io_pydata_format.py
graphit/graph_io/io_tgf_format.py
graphit/graph_io/io_web_format.py
graphit/graph_io/io_xml_format.py
graphit/graph_io/io_yaml_format.py
graphit/graph_model_classes/__init__.py
graphit/graph_model_classes/model_datetime.py
graphit/graph_model_classes/model_dictionary.py
graphit/graph_model_classes/model_email.py
graphit/graph_model_classes/model_files.py
graphit/graph_model_classes/model_identifiers.py
graphit/graph_model_classes/model_networking.py
graphit/graph_model_classes/model_openapi.py
graphit/graph_model_classes/model_user.py
graphit/graph_query/__init__.py
graphit/graph_query/graph_query.py
graphit/graph_query/query_xpath.py
graphit/graph_storage_drivers/__init__.py
graphit/graph_storage_drivers/graph_arraystorage_driver.py
py_graphit-0.2.1.dist-info/DESCRIPTION.rst
py_graphit-0.2.1.dist-info/METADATA
py_graphit-0.2.1.dist-info/RECORD
py_graphit-0.2.1.dist-info/WHEEL
py_graphit-0.2.1.dist-info/metadata.json
py_graphit-0.2.1.dist-info/top_level.txt
py_graphit-0.2.1.dist-info/zip-safe
