Metadata-Version: 2.0
Name: py-graphit
Version: 0.2.1
Summary: Graph based data handling for the MDStudio application
Home-page: https://graphit.github.io
Author: Marc van Dijk - VU University - Amsterdam,
Author-email: m4.van.dijk@vu.nl
License: Apache Software License 2.0
Keywords: graph data ORM
Platform: Any
Classifier: License :: OSI Approved :: Apache Software License
Classifier: Programming Language :: Python
Classifier: Topic :: Software Development :: Libraries
Classifier: Operating System :: OS Independent
Classifier: Intended Audience :: Science/Research
Provides-Extra: test
Requires-Dist: python-dateutil
Requires-Dist: pytz
Requires-Dist: uritools
Provides-Extra: test
Requires-Dist: PyYAML; extra == 'test'
Requires-Dist: coverage; extra == 'test'
